pySSRSapi/__init__.py
src/SsrsApi.py
src/__init__.py
pySSRSapi-0.0.22.dist-info/METADATA
pySSRSapi-0.0.22.dist-info/WHEEL
pySSRSapi-0.0.22.dist-info/top_level.txt
pySSRSapi-0.0.22.dist-info/RECORD
