Metadata-Version: 2.1
Name: pySSRSapi
Version: 0.0.22
Summary: Python SSRS API
Home-page: https://pypi.org/project/pySSRSapi/
Author: quaik8
Author-email: mail@example.com
License: MIT license
Keywords: SSRS,API
Classifier: Development Status :: 5 - Production/Stable
Classifier: Intended Audience :: Developers
Classifier: License :: OSI Approved :: MIT License
Classifier: Natural Language :: English
Classifier: Programming Language :: Python :: 3.7
Requires-Python: >=3.7
Requires-Dist: requests
